nova_act/__init__.py
nova_act/__version__.py
nova_act/nova_act.py
nova_act/py.typed
nova_act/cli/__init__.py
nova_act/cli/__version__.py
nova_act/cli/cli.py
nova_act/cli/group.py
nova_act/cli/core/__init__.py
nova_act/cli/core/config.py
nova_act/cli/core/constants.py
nova_act/cli/core/error_detection.py
nova_act/cli/core/exceptions.py
nova_act/cli/core/identity.py
nova_act/cli/core/logging.py
nova_act/cli/core/region.py
nova_act/cli/core/state_manager.py
nova_act/cli/core/styling.py
nova_act/cli/core/theme.py
nova_act/cli/core/types.py
nova_act/cli/core/user_config_manager.py
nova_act/cli/core/clients/__init__.py
nova_act/cli/core/clients/agentcore/__init__.py
nova_act/cli/core/clients/agentcore/client.py
nova_act/cli/core/clients/agentcore/constants.py
nova_act/cli/core/clients/agentcore/response_parser.py
nova_act/cli/core/clients/agentcore/types.py
nova_act/cli/core/clients/ecr/__init__.py
nova_act/cli/core/clients/ecr/client.py
nova_act/cli/core/clients/ecr/constants.py
nova_act/cli/core/clients/iam/__init__.py
nova_act/cli/core/clients/iam/client.py
nova_act/cli/core/clients/iam/types.py
nova_act/cli/core/clients/nova_act/__init__.py
nova_act/cli/core/clients/nova_act/client.py
nova_act/cli/core/clients/nova_act/constants.py
nova_act/cli/core/clients/nova_act/types.py
nova_act/cli/core/clients/s3/__init__.py
nova_act/cli/core/clients/s3/client.py
nova_act/cli/workflow/__init__.py
nova_act/cli/workflow/workflow_deployer.py
nova_act/cli/workflow/workflow_manager.py
nova_act/cli/workflow/commands/__init__.py
nova_act/cli/workflow/commands/create.py
nova_act/cli/workflow/commands/delete.py
nova_act/cli/workflow/commands/deploy.py
nova_act/cli/workflow/commands/list.py
nova_act/cli/workflow/commands/run.py
nova_act/cli/workflow/commands/show.py
nova_act/cli/workflow/commands/update.py
nova_act/cli/workflow/services/__init__.py
nova_act/cli/workflow/services/constants.py
nova_act/cli/workflow/services/agentcore/__init__.py
nova_act-3.1.89.0.dist-info/licenses/LICENSE
nova_act-3.1.89.0.dist-info/licenses/NOTICE
nova_act-3.1.89.0.dist-info/METADATA
nova_act-3.1.89.0.dist-info/WHEEL
nova_act-3.1.89.0.dist-info/entry_points.txt
nova_act-3.1.89.0.dist-info/top_level.txt
nova_act-3.1.89.0.dist-info/RECORD
