Metadata-Version: 2.4
Name: nova-act
Version: 3.1.89.0
Summary: A Python SDK for Amazon Nova Act.
Author-email: Amazon Nova Act <nova-act@amazon.com>
License-Expression: Apache-2.0
Requires-Python: >=3.10
License-File: LICENSE
License-File: NOTICE
Requires-Dist: cryptography
Requires-Dist: fire
Requires-Dist: install_playwright<1.0.0,>=0.1.0
Requires-Dist: jsonschema
Requires-Dist: numpy<=2.2.6
Requires-Dist: pandas
Requires-Dist: pillow
Requires-Dist: playwright<=1.56.0,>=1.54.0
Requires-Dist: pydantic>=2.10.6
Requires-Dist: requests
Requires-Dist: retry
Requires-Dist: tenacity
Requires-Dist: pytz
Requires-Dist: strands-agents<=1.23.0,>=1.2.0
Requires-Dist: strands-agents-tools<=0.2.19
Requires-Dist: Deprecated
Requires-Dist: boto3>=1.42.1
Requires-Dist: boto3-stubs
Requires-Dist: mypy-boto3-s3
Provides-Extra: dev
Requires-Dist: build; extra == "dev"
Requires-Dist: setuptools; extra == "dev"
Requires-Dist: twine; extra == "dev"
Requires-Dist: wheel; extra == "dev"
Requires-Dist: mypy; extra == "dev"
Requires-Dist: boto3-stubs; extra == "dev"
Provides-Extra: cli
Requires-Dist: click; extra == "cli"
Requires-Dist: pyyaml; extra == "cli"
Dynamic: license-file
